main.py
numpy_mcp-0.1.0.dist-info/METADATA
numpy_mcp-0.1.0.dist-info/WHEEL
numpy_mcp-0.1.0.dist-info/top_level.txt
numpy_mcp-0.1.0.dist-info/RECORD
