Metadata-Version: 2.4
Name: numpy-mcp
Version: 0.1.0
Summary: Add your description here
Requires-Python: >=3.10
Requires-Dist: mcp>=1.9.2
Requires-Dist: numpy>=2.2.6
